linguars-0.4.0.dist-info/METADATA
linguars-0.4.0.dist-info/WHEEL
linguars/__init__.py
linguars/__init__.pyi
linguars/py.typed
linguars/linguars.abi3.so
linguars-0.4.0.dist-info/RECORD
