Metadata-Version: 2.1
Name: linguars
Version: 0.4.0
Summary: lingua-rs Python binding
License: MIT
Project-URL: Source Code, https://github.com/messense/lingua-py
